auth0_component/__init__.py
streamlit_auth0_component_pw1-0.0.1.dist-info/LICENSE
streamlit_auth0_component_pw1-0.0.1.dist-info/METADATA
streamlit_auth0_component_pw1-0.0.1.dist-info/WHEEL
streamlit_auth0_component_pw1-0.0.1.dist-info/top_level.txt
streamlit_auth0_component_pw1-0.0.1.dist-info/RECORD
