Metadata-Version: 2.1
Name: streamlit-auth0-component-pw1
Version: 0.0.1
Home-page: 
Author: 
Author-email: 
Requires-Python: >=3.6
License-File: LICENSE
Requires-Dist: streamlit >=0.63
Requires-Dist: python-jose ==3.3.0
